MANIFEST.in
README.rst
manage.py
run_test_and_report.sh
setup.py
tests.py
djmongo/__init__.py
djmongo/document.py
djmongo/exceptions.py
djmongo/models.py
djmongo/test.py
djmongo/testsettings.py
djmongo/utils.py
djmongo.egg-info/PKG-INFO
djmongo.egg-info/SOURCES.txt
djmongo.egg-info/dependency_links.txt
djmongo.egg-info/not-zip-safe
djmongo.egg-info/requires.txt
djmongo.egg-info/top_level.txt
djmongo/backend/__init__.py
djmongo/backend/mongodb/__init__.py
djmongo/backend/mongodb/base.py
djmongo/tests/__init__.py
djmongo/tests/test_db.py
djmongo/tests/test_document.py
djmongo/tests/test_manager.py
djmongo/tests/test_test_case.py