Metadata-Version: 1.0
Name: djmongo
Version: 0.1.2
Summary: Implementation of per object permissions for Django 1.2 or later.
Home-page: http://github.com/lukaszb/djmongo
Author: Lukasz Balcerzak
Author-email: lukaszbalcerzak@gmail.com
License: BSD
Download-URL: http://github.com/lukaszb/djmongo/downloads
Platform: UNKNOWN
Classifier: Development Status :: 5 - Production/Stable
Classifier: Environment :: Web Environment
Classifier: Framework :: Django
Classifier: Intended Audience :: Developers
Classifier: Operating System :: OS Independent
Classifier: Programming Language :: Python
Classifier: Topic :: Security
